odoo/addons/fieldservice_repair/README.rst
odoo/addons/fieldservice_repair/__init__.py
odoo/addons/fieldservice_repair/__manifest__.py
odoo/addons/fieldservice_repair/data/fsm_order_type.xml
odoo/addons/fieldservice_repair/i18n/de.po
odoo/addons/fieldservice_repair/i18n/es.po
odoo/addons/fieldservice_repair/i18n/es_AR.po
odoo/addons/fieldservice_repair/i18n/fieldservice_repair.pot
odoo/addons/fieldservice_repair/i18n/it.po
odoo/addons/fieldservice_repair/i18n/pt_BR.po
odoo/addons/fieldservice_repair/models/__init__.py
odoo/addons/fieldservice_repair/models/fsm_order.py
odoo/addons/fieldservice_repair/models/fsm_order_type.py
odoo/addons/fieldservice_repair/readme/CONFIGURE.rst
odoo/addons/fieldservice_repair/readme/CONTRIBUTORS.rst
odoo/addons/fieldservice_repair/readme/CREDITS.rst
odoo/addons/fieldservice_repair/readme/DESCRIPTION.rst
odoo/addons/fieldservice_repair/readme/INSTALL.rst
odoo/addons/fieldservice_repair/readme/ROADMAP.rst
odoo/addons/fieldservice_repair/readme/USAGE.rst
odoo/addons/fieldservice_repair/static/description/icon.png
odoo/addons/fieldservice_repair/static/description/index.html
odoo/addons/fieldservice_repair/tests/__init__.py
odoo/addons/fieldservice_repair/tests/test_fsm_repair.py
odoo/addons/fieldservice_repair/views/fsm_order_view.xml
odoo14_addon_fieldservice_repair-14.0.1.0.1.dev12.dist-info/METADATA
odoo14_addon_fieldservice_repair-14.0.1.0.1.dev12.dist-info/WHEEL
odoo14_addon_fieldservice_repair-14.0.1.0.1.dev12.dist-info/top_level.txt
odoo14_addon_fieldservice_repair-14.0.1.0.1.dev12.dist-info/RECORD
